agentpod/__init__.py
agentpod/client/__init__.py
agentpod/client/client.py
agentpod/client/structured/LICENSE
agentpod/client/structured/__init__.py
agentpod/client/structured/custom_async_openai.py
agentpod/client/structured/dsl/citation.py
agentpod/client/structured/dsl/iterable.py
agentpod/client/structured/dsl/maybe.py
agentpod/client/structured/dsl/parallel.py
agentpod/client/structured/dsl/partial.py
agentpod/client/structured/dsl/simple_type.py
agentpod/client/structured/dsl/validators.py
agentpod/client/structured/exceptions.py
agentpod/client/structured/function_calls.py
agentpod/client/structured/mode.py
agentpod/client/structured/patch.py
agentpod/client/structured/process_response.py
agentpod/client/structured/retry.py
agentpod/client/structured/utils.py
agentpod/http/__init__.py
agentpod/http/client.py
agentpod/http/retry_transport.py
agentpod/tools/__init__.py
agentpod/tools/bing.py
agentpod/utils/__init__.py
agentpod/utils/contentizer.py
agentpod/utils/file_cache.py
agentpod/utils/tracker.py
agentpod/utils/utils.py
agentpod-0.1.6.dist-info/LICENSE
agentpod-0.1.6.dist-info/METADATA
agentpod-0.1.6.dist-info/NOTICE
agentpod-0.1.6.dist-info/WHEEL
agentpod-0.1.6.dist-info/RECORD
