Metadata-Version: 2.1
Name: agentpod
Version: 0.1.6
Summary: A simple framework for agentic systems
Home-page: https://agentpod.ai
License: MIT
Author: Boat Builder
Author-email: hello@boatbuilder.dev
Requires-Python: >=3.11,<4.0
Classifier: Development Status :: 4 - Beta
Classifier: Intended Audience :: Developers
Classifier: License :: OSI Approved :: MIT License
Classifier: Programming Language :: Python :: 3
Classifier: Programming Language :: Python :: 3.11
Classifier: Programming Language :: Python :: 3.12
Classifier: Topic :: Scientific/Engineering :: Artificial Intelligence
Classifier: Topic :: Software Development :: Libraries
Requires-Dist: azure-cognitiveservices-search-websearch (>=2.0.1,<3.0.0)
Requires-Dist: bs4 (>=0.0.2,<0.0.3)
Requires-Dist: docstring-parser (>=0.16,<0.17)
Requires-Dist: loguru (>=0.7.2,<0.8.0)
Requires-Dist: numpy (<2.0.0)
Requires-Dist: openai (>=1.32.0,<2.0.0)
Requires-Dist: pydantic (>=2.7.3,<3.0.0)
Requires-Dist: python-dateutil (>=2.9.0.post0,<3.0.0)
Requires-Dist: requests (>=2.32.3,<3.0.0)
Requires-Dist: tenacity (>=8.3.0,<9.0.0)
Project-URL: Documentation, https://github.com/boat-builder/agentpod
Project-URL: Repository, https://github.com/boat-builder/agentpod
